tbd/__about__.py
tbd/__init__.py
tbd/evaluate.py
tbd/model.py
tbd/predict.py
tbd/preprocessing.py
tbd/utils.py
tbd/pretrained_model/saved_model.pb
tbd/pretrained_model/variables/variables.data-00000-of-00001
tbd/pretrained_model/variables/variables.index
TauBD-1.0.dist-info/LICENSE
TauBD-1.0.dist-info/METADATA
TauBD-1.0.dist-info/WHEEL
TauBD-1.0.dist-info/top_level.txt
TauBD-1.0.dist-info/RECORD
