Metadata-Version: 2.1
Name: TauBD
Version: 1.0
Summary: TBD: Tau Be Damned.
Home-page: https://github.com/Intrinsically-Disordered/TBD
Author: TBD
Author-email: hjwgogo@gmail.com
License: MIT License
Platform: UNKNOWN
License-File: LICENSE
Requires-Dist: numpy
Requires-Dist: scipy
Requires-Dist: pandas
Requires-Dist: scikit-learn
Requires-Dist: tensorflow
Provides-Extra: dev
Requires-Dist: pytest ; extra == 'dev'
Provides-Extra: docs
Provides-Extra: test
Requires-Dist: pytest ; extra == 'test'
